python_environment_settings.py
python_environment_settings-0.1.1.dist-info/LICENSE
python_environment_settings-0.1.1.dist-info/METADATA
python_environment_settings-0.1.1.dist-info/WHEEL
python_environment_settings-0.1.1.dist-info/top_level.txt
python_environment_settings-0.1.1.dist-info/RECORD
