Metadata-Version: 2.1
Name: python-environment-settings
Version: 0.1.1
Summary: 简易的配置项获取方式，支持添加多种配置项获取源。默认从环境变量中获取配置项。
Author: rRR0VrFP
Maintainer: rRR0VrFP
License: Apache License, Version 2.0
Keywords: python-environment-settings
Classifier: Development Status :: 5 - Production/Stable
Classifier: Intended Audience :: Developers
Classifier: Topic :: Software Development :: Libraries :: Python Modules
Classifier: License :: OSI Approved :: Apache Software License
Classifier: Programming Language :: Python :: 3
Classifier: Programming Language :: Python :: 3 :: Only
License-File: LICENSE
Requires-Dist: null-object
